{
   "files": [    



{
         "name": "FREE-TH-01-AIS",
         "url": "https://raw.githubusercontent.com/GODNET2003/INTERNET/main/Ais1.ovpn"
      }
,
{
         "name": "FREE-TH-01-DTAC",
         "url": "https://raw.githubusercontent.com/GODNET2003/INTERNET/main/Dtac1.ovpn"
      }
,
{
         "name": "FREE-TH-01-TRUE",
         "url": "https://raw.githubusercontent.com/GODNET2003/INTERNET/main/True1.ovpn"
      }
,
{
         "name": "FREE-TH-02-AIS",
         "url": "https://raw.githubusercontent.com/GODNET2003/INTERNET/main/Ais2.ovpn"
      }
,
{
         "name": "FREE-TH-02-DTAC",
         "url": "https://raw.githubusercontent.com/GODNET2003/INTERNET/main/Dtac2.ovpn"
      }
,
{
         "name": "FREE-TH-02-TRUE",
         "url": "https://raw.githubusercontent.com/GODNET2003/INTERNET/main/True2.ovpn"
      }



   ],
"message":"
■■■■■■■■■■■■■■■■■■
👑บริการจัดการโดยทีมงานแอดมิน
■■■■■■■■■■■■■■■■■■
✅️ใช้งานฟรี
✅️ประหยัดเงิน
✅️สะดวก และปลอดภัย
■■■■■■■■■■■■■■■■■■
❗️มีปัญหาติดต่อแอดมิน
❗️ได้ที่ปุ่มได้เลยครับ
■■■■■■■■■■■■■■■■■■
❤️ขอให้สนุกกับการใช้งานครับ
■■■■■■■■■■■■■■■■■■


\n\nเวอร์ชั่นไฟล์:1.11",
"title":"New Update File" ,
   "version":2
}
